{"name":"993 Joe Freshgoods Performance Art - Arctic Blue","sizes":[["US 4","Уведомить меня"],["US 4.5","Уведомить меня"],["US 5","Уведомить меня"],["US 5.5","Уведомить меня"],["US 6","Уведомить меня"],["US 6.5","Уведомить меня"],["US 7","38.000"],["US 7.5","46.000"],["US 8","44.000"],["US 8.5","45.000"],["US 9","40.000"],["US 9.5","46.000"],["US 10","49.000"],["US 10.5","47.000"],["US 11","38.000"],["US 11.5","45.000"],["US 12","59.000"],["US 12.5","Уведомить меня"],["US 13","56.000"],["US 14","123.000"]],"description":"v","article":"MR993JF1","date":"\n7 октября 2022\n"}